home_assistant_eltako_frontend/__init__.py
home_assistant_eltako_frontend/static/__init__.py
home_assistant_eltako_frontend/static/assets/index-Bce-RCVh.js
home_assistant_eltako_frontend/static/assets/parameters-bundle.css-B0qPXqYP.js
home_assistant_eltako_frontend/static/assets/parameters-bundle.css-BHsfFId7.js
home_assistant_eltako_frontend/static/assets/parameters-bundle.css-CDvu_k5f.js
home_assistant_eltako_frontend/static/assets/parameters-bundle.css-CQtjpUxA.js
home_assistant_eltako_frontend/static/assets/parameters-bundle.css-Cg7peeD5.js
home_assistant_eltako_frontend/static/assets/parameters-bundle.css-ClbbINbL.js
home_assistant_eltako_frontend/static/assets/parameters-bundle.css-Cqkvdl_8.js
home_assistant_eltako_frontend/static/assets/parameters-bundle.css-DTU5fWUH.js
home_assistant_eltako_frontend/static/assets/parameters-bundle.css-DiA2eI41.js
home_assistant_eltako_frontend/static/assets/parameters-bundle.css-Xr8mFjYv.js
home_assistant_eltako_frontend/static/assets/parameters-bundle.css-cxhU8kDT.js
home_assistant_eltako_frontend/static/assets/parameters-bundle.css-ttcDIoz1.js
home_assistant_eltako_frontend/static/index.html
home_assistant_eltako_frontend-0.0.21.dist-info/LICENSE
home_assistant_eltako_frontend-0.0.21.dist-info/METADATA
home_assistant_eltako_frontend-0.0.21.dist-info/WHEEL
home_assistant_eltako_frontend-0.0.21.dist-info/entry_points.txt
home_assistant_eltako_frontend-0.0.21.dist-info/RECORD
